remotekernel/__init__.py
remotekernel/_version.py
remotekernel/kernelspec.py
remotekernel/manager.py
remotekernel-0.2.4.dist-info/DESCRIPTION.rst
remotekernel-0.2.4.dist-info/METADATA
remotekernel-0.2.4.dist-info/RECORD
remotekernel-0.2.4.dist-info/WHEEL
remotekernel-0.2.4.dist-info/metadata.json
remotekernel-0.2.4.dist-info/top_level.txt
