Metadata-Version: 2.0
Name: remotekernel
Version: 0.2.4
Summary: A custom KernelManager for launching remote IPython kernels
Home-page: http://github.com/danielballan/remotekernel
Author: Brookhaven National Laboratory
Author-email: UNKNOWN
License: UNKNOWN
Platform: Cross platform (Linux
Platform: Mac OSX
Platform: Windows)
